<annotation>
	<folder>images</folder>
	<filename>323.jpg</filename>
	<path>C:\Users\choi\object_detection_demo\data\images\323.jpg</path>
	<source>
		<database>Unknown</database>
	</source>
	<size>
		<width>720</width>
		<height>720</height>
		<depth>1</depth>
	</size>
	<segmented>0</segmented>
	<object>
		<name>child</name>
		<pose>Unspecified</pose>
		<truncated>0</truncated>
		<difficult>0</difficult>
		<bndbox>
			<xmin>504</xmin>
			<ymin>132</ymin>
			<xmax>553</xmax>
			<ymax>216</ymax>
		</bndbox>
	</object>
</annotation>
