<annotation>
	<folder>left</folder>
	<filename>left (28).jpg</filename>
	<path>C:\Users\choi\Dropbox\PostNomad\Vision\data\resize\left\left (28).jpg</path>
	<source>
		<database>Unknown</database>
	</source>
	<size>
		<width>720</width>
		<height>720</height>
		<depth>3</depth>
	</size>
	<segmented>0</segmented>
	<object>
		<name>left</name>
		<pose>Unspecified</pose>
		<truncated>0</truncated>
		<difficult>0</difficult>
		<bndbox>
			<xmin>264</xmin>
			<ymin>251</ymin>
			<xmax>329</xmax>
			<ymax>332</ymax>
		</bndbox>
	</object>
</annotation>
